awsprofile/__init__.py
aws_profile-0.6.1.dist-info/METADATA
aws_profile-0.6.1.dist-info/WHEEL
aws_profile-0.6.1.dist-info/entry_points.txt
aws_profile-0.6.1.dist-info/top_level.txt
aws_profile-0.6.1.dist-info/RECORD
