Metadata-Version: 2.1
Name: aws-profile
Version: 0.6.1
Summary: A wrapper for executing a command using AWS Assumed Role
Home-page: https://github.com/jrstarke/aws-profile
Author: Jamie Starke
Author-email: github@jamiestarke.com
License: UNKNOWN
Keywords: aws profile assume role
Platform: UNKNOWN
Classifier: Development Status :: 4 - Beta
Classifier: Intended Audience :: Developers
Classifier: Programming Language :: Python :: 2
Classifier: Programming Language :: Python :: 2.7
Classifier: Programming Language :: Python :: 3
Classifier: Programming Language :: Python :: 3.4
Classifier: Programming Language :: Python :: 3.5
Classifier: Programming Language :: Python :: 3.6
Classifier: Programming Language :: Python :: 3.7
Classifier: Programming Language :: Python :: 3.8
Requires-Dist: botocore (>=1.3.15)
Requires-Dist: awscli (>=1.14.10)
Provides-Extra: dev
Requires-Dist: pytest ; extra == 'dev'
Requires-Dist: pytest-cov ; extra == 'dev'
Requires-Dist: pytest-mock ; extra == 'dev'
Requires-Dist: coveralls ; extra == 'dev'
